CHANGES.txt
MANIFEST.in
README.txt
setup.cfg
setup.py
docs/Makefile
docs/conf.py
docs/index.rst
docs/make.bat
plonesocial/__init__.py
plonesocial.twitter.anywhere.egg-info/PKG-INFO
plonesocial.twitter.anywhere.egg-info/SOURCES.txt
plonesocial.twitter.anywhere.egg-info/dependency_links.txt
plonesocial.twitter.anywhere.egg-info/entry_points.txt
plonesocial.twitter.anywhere.egg-info/namespace_packages.txt
plonesocial.twitter.anywhere.egg-info/not-zip-safe
plonesocial.twitter.anywhere.egg-info/paster_plugins.txt
plonesocial.twitter.anywhere.egg-info/requires.txt
plonesocial.twitter.anywhere.egg-info/top_level.txt
plonesocial/twitter/__init__.py
plonesocial/twitter/anywhere/__init__.py
plonesocial/twitter/anywhere/configure.zcml
plonesocial/twitter/anywhere/browser/__init__.py
plonesocial/twitter/anywhere/browser/anywhere.js
plonesocial/twitter/anywhere/browser/configlet.py
plonesocial/twitter/anywhere/browser/configure.zcml
plonesocial/twitter/anywhere/browser/twitter.png
plonesocial/twitter/anywhere/browser/viewlets.py
plonesocial/twitter/anywhere/portlets/__init__.py
plonesocial/twitter/anywhere/portlets/configure.zcml
plonesocial/twitter/anywhere/portlets/tweetbox.pt
plonesocial/twitter/anywhere/portlets/tweetbox.py
plonesocial/twitter/anywhere/portlets/twitterbutton.pt
plonesocial/twitter/anywhere/portlets/twitterbutton.py
plonesocial/twitter/anywhere/profiles/default/controlpanel.xml
plonesocial/twitter/anywhere/profiles/default/jsregistry.xml
plonesocial/twitter/anywhere/profiles/default/portlets.xml
plonesocial/twitter/anywhere/profiles/default/propertiestool.xml