Metadata-Version: 1.0
Name: plonesocial.twitter.anywhere
Version: 0.1
Summary: Twitter @Anywhere integration to Plone
Home-page: http://comlounge.net/anywhere
Author: Christian Scholz
Author-email: cs@comlounge.net
License: MIT
Keywords: plone plonesocial twitter anywhere socialnetworks socialweb web tweets follow cms
Platform: UNKNOWN
Classifier: Development Status :: 4 - Beta
Classifier: Environment :: Web Environment
Classifier: Framework :: Plone
Classifier: Framework :: Zope2
Classifier: Intended Audience :: Developers
Classifier: Intended Audience :: End Users/Desktop
Classifier: Intended Audience :: System Administrators
Classifier: License :: OSI Approved :: MIT License
Classifier: Operating System :: OS Independent
Classifier: Programming Language :: Python
Classifier: Programming Language :: Python :: 2
Classifier: Topic :: Internet :: WWW/HTTP
Classifier: Topic :: Internet :: WWW/HTTP :: Site Management
